Workbook

Sheet CRM_Leads
A1: Lead_ID | B1: Client_Type (B2B/B2C) | C1: Company/Client Name | D1: Contact Person | E1: Phone | F1: Email | G1: Object Type | H1: Area (m2) | I1: Service Type | J1: Estimated Budget | K1: Stage (Lead/Proposal/Contract/Done) | L1: Probability (%) | M1: Expected Revenue | N1: Source | O1: Manager | P1: Created Date | Q1: Next Action | R1: Notes

Sheet B2B_Pricing
A1: Service | B1: Category | C1: Base Cost (RUB) | D1: Material Cost (RUB) | E1: Labor Cost (RUB) | F1: Total Cost | G1: Recommended Price | H1: Margin (%)
A2: APS | B2: Project | C2: 150000 | D2: 0 | E2: 90000 | F2: =C2+D2+E2 | G2: =F2*1.35 | H2: =((G2-F2)/G2)*100
A3: CCTV | B3: Installation (10 cameras) | C3: 400000 | D3: 250000 | E3: 100000 | F3: =C3+D3+E3 | G3: =F3*1.30 | H3: =((G3-F3)/G3)*100
A4: Access Control | B4: Office 50 users | C4: 700000 | D4: 400000 | E4: 200000 | F4: =C4+D4+E4 | G4: =F4*1.30 | H4: =((G4-F4)/G4)*100

Sheet B2C_Pricing
A1: Service | B1: Unit | C1: Cost (RUB) | D1: Recommended Retail Price (RUB) | E1: Margin (%)
A2: Camera Installation | B2: per unit | C2: 3000 | D2: 5000 | E2: =((D2-C2)/D2)*100
A3: Smoke Detector Install | B3: per unit | C3: 1200 | D3: 2500 | E3: =((D3-C3)/D3)*100
A4: Electrical Panel Install | B4: per unit | C4: 25000 | D4: 40000 | E4: =((D4-C4)/D4)*100

Sheet Unit_Economics
A1: Metric | B1: Value
A2: Average Deal Size (B2B) | B2: 5000000
A3: Average Deal Size (B2C) | B3: 120000
A4: Average Gross Margin (%) | B4: 30
A5: Customer Acquisition Cost (CAC) | B5: 50000
A6: Monthly Service Revenue (Avg) | B6: 15000
A7: Client Lifetime (Years) | B7: 5
A8: LTV (Formula) | B8: =B6*12*B5

Sheet Commercial_Template
A1: Section | B1: Description
A2: Company Overview | B2: Brief description of company expertise and licenses
A3: Scope of Work | B3: Detailed list of systems and integration scope
A4: Technical Solution | B4: Architecture and integration logic
A5: Project Timeline | B5: Estimated duration and milestones
A6: Cost Breakdown | B6: Equipment, labor, commissioning
A7: Service Agreement | B7: Maintenance terms and SLA
A8: Total Investment | B8: Final commercial offer with validity period

Sheet Project_PnL
A1: Project Name | B1: Revenue | C1: Equipment Cost | D1: Labor Cost | E1: Subcontract Cost | F1: Overhead Allocation | G1: Total Cost | H1: Gross Profit | I1: Gross Margin (%)
A2: Sample Project | B2: 5000000 | C2: 2500000 | D2: 800000 | E2: 300000 | F2: 200000 | G2: =C2+D2+E2+F2 | H2: =B2-G2 | I2: =H2/B2*100

Sheet Cashflow_Forecast
A1: Month | B1: Opening Balance | C1: Incoming (Contracts) | D1: Outgoing (Costs) | E1: Net Cashflow | F1: Closing Balance
A2: Month 1 | E2: =C2-D2 | F2: =B2+E2
A3: Month 2 | E3: =C3-D3 | F3: =B3+E3
A4: Month 3 | E4: =C4-D4 | F4: =B4+E4
A5: Month 4 | E5: =C5-D5 | F5: =B5+E5
A6: Month 5 | E6: =C6-D6 | F6: =B6+E6
A7: Month 6 | E7: =C7-D7 | F7: =B7+E7
A8: Month 7 | E8: =C8-D8 | F8: =B8+E8
A9: Month 8 | E9: =C9-D9 | F9: =B9+E9
A10: Month 9 | E10: =C10-D10 | F10: =B10+E10
A11: Month 10 | E11: =C11-D11 | F11: =B11+E11
A12: Month 11 | E12: =C12-D12 | F12: =B12+E12
A13: Month 12 | E13: =C13-D13 | F13: =B13+E13

Sheet Payroll_Model
A1: Role | B1: Number of Employees | C1: Average Salary | D1: Total Salary Cost | E1: Taxes & Contributions (30%) | F1: Total Employer Cost
A2: Engineers | B2: 5 | C2: 120000 | D2: =B2*C2 | E2: =D2*0.30 | F2: =D2+E2
A3: Installers | B3: 10 | C3: 90000 | D3: =B3*C3 | E3: =D3*0.30 | F3: =D3+E3

Sheet Warehouse_Model
A1: Item | B1: Purchase Price | C1: Stock Quantity | D1: Total Stock Value | E1: Average Monthly Usage | F1: Reorder Point
A2: Smoke Detector | B2: 1500 | C2: 500 | D2: =B2*C2 | E2: 120 | F2: =E2*1.5
A3: IP Camera | B3: 8000 | C3: 120 | D3: =B3*C3 | E3: 25 | F3: =E3*1.5

Sheet KPI_Dashboard
A1: Metric | B1: Formula/Value
A2: Total Revenue (All Projects) | B2: =SUM(Project_PnL!B2:B100)
A3: Total Gross Profit | B3: =SUM(Project_PnL!H2:H100)
A4: Average Gross Margin | B4: =AVERAGE(Project_PnL!I2:I100)
A5: Monthly Payroll Cost | B5: =SUM(Payroll_Model!F2:F10)
A6: Inventory Value | B6: =SUM(Warehouse_Model!D2:D100)
